<?xml version="1.0" encoding="utf-8"?>
<Tables xmlns:xs="http://www.w3.org/2001/XMLSchema-instance" xs:schemaLocation="http://www.newlifex.com https://raw.githubusercontent.com/NewLifeX/X/master/XCode/Model2020.xsd" NameSpace="COMCMS.Core" ConnName="dbconn" Output="" BaseClass="Entity" xmlns="http://www.newlifex.com/Model2020.xsd">
  <Table Name="Admin" Description="管理员" DbType="SqlServer">
    <Columns>
      <Column Name="Id" DataType="Int32" Identity="True" PrimaryKey="True" Description="编号" />
      <Column Name="UserName" DataType="String" Master="True" Length="20" Description="用户名" />
      <Column Name="PassWord" DataType="String" Description="密码" />
      <Column Name="Salt" DataType="String" Length="20" Description="盐值" />
      <Column Name="RealName" DataType="String" Length="20" Description="姓名" />
      <Column Name="Tel" DataType="String" Length="20" Description="电话" />
      <Column Name="Email" DataType="String" Master="True" Length="100" Description="邮件" />
      <Column Name="UserLevel" DataType="Int32" Description="级别" />
      <Column Name="RoleId" DataType="Int32" Master="True" Description="管理组" />
      <Column Name="GroupId" DataType="Int32" Master="True" Description="用户组" />
      <Column Name="LastLoginTime" DataType="DateTime" Description="最后登录时间" />
      <Column Name="LastLoginIP" DataType="String" Length="20" Description="上次登录IP" />
      <Column Name="ThisLoginTime" DataType="DateTime" Description="本次登录时间" />
      <Column Name="ThisLoginIP" DataType="String" Length="20" Description="本次登录IP" />
      <Column Name="IsLock" DataType="Int32" Description="是否是锁定" />
    </Columns>
  </Table>
  <Table Name="AdminRoles" Description="管理角色" DbType="SqlServer">
    <Columns>
      <Column Name="Id" DataType="Int32" Identity="True" PrimaryKey="True" Description="编号" />
      <Column Name="RoleType" DataType="Int32" Description="角色类型" />
      <Column Name="RoleName" DataType="String" Master="True" Description="角色名称" />
      <Column Name="RoleDescription" DataType="String" Master="True" Length="250" Description="角色简单介绍" />
      <Column Name="IsSuperAdmin" DataType="Int32" Description="是否是超级管理员" />
      <Column Name="Stars" DataType="Int32" Description="星级" />
      <Column Name="NotAllowDel" DataType="Int32" Description="是否不允许删除" />
      <Column Name="Rank" DataType="Int32" Description="排序" />
      <Column Name="Color" DataType="String" Master="True" Length="20" Description="颜色" />
      <Column Name="Menus" DataType="String" Master="True" Length="-1" Description="管理菜单" />
      <Column Name="Powers" DataType="String" Master="True" Length="-1" Description="权限" />
      <Column Name="AuthorizedArticleCagegory" DataType="String" Master="True" Length="-1" Description="已授权文章栏目" />
      <Column Name="AuthorizedCagegory" DataType="String" Master="True" Length="-1" Description="已授权商品栏目" />
      <Column Name="OnlyEditMyselfArticle" DataType="Int32" Description="是否只允许编辑自己的文章" />
      <Column Name="OnlyEditMyselfProduct" DataType="Int32" Description="是否只允许编辑自己的产品" />
    </Columns>
  </Table>
  <Table Name="AdminLog" Description="管理日志表" DbType="SqlServer">
    <Columns>
      <Column Name="Id" DataType="Int32" Identity="True" PrimaryKey="True" Description="编号" />
      <Column Name="UId" DataType="Int32" Master="True" Description="管理员ID" />
      <Column Name="Guid" DataType="String" Description="唯一ID" />
      <Column Name="UserName" DataType="String" Master="True" Length="20" Description="用户名" />
      <Column Name="PassWord" DataType="String" Description="密码" />
      <Column Name="LoginTime" DataType="DateTime" Description="登录时间" />
      <Column Name="LoginIP" DataType="String" Length="20" Description="登录IP" />
      <Column Name="IsLoginOK" DataType="Int32" Description="是否登录成功" />
      <Column Name="Actions" DataType="String" Master="True" Length="-1" Description="记录" />
      <Column Name="LastUpdateTime" DataType="DateTime" Description="登录时间" />
    </Columns>
  </Table>
  <Table Name="TargetEvent" Description="目标事件" DbType="SqlServer">
    <Columns>
      <Column Name="Id" DataType="Int32" Identity="True" PrimaryKey="True" Description="编号" />
      <Column Name="EventKey" DataType="String" Master="True" Description="事件key" />
      <Column Name="EventName" DataType="String" Description="事件名称" />
      <Column Name="IsDisable" DataType="Int32" Description="是否禁用" />
      <Column Name="Rank" DataType="Int32" Description="排序" />
    </Columns>
  </Table>
  <Table Name="AdminMenu" Description="后台菜单" DbType="SqlServer">
    <Columns>
      <Column Name="Id" DataType="Int32" Identity="True" PrimaryKey="True" Description="编号" />
      <Column Name="MenuKey" DataType="String" Master="True" Description="标识key" />
      <Column Name="MenuName" DataType="String" Description="页面名称" />
      <Column Name="PermissionKey" DataType="String" Description="页面名称" />
      <Column Name="Description" DataType="String" Length="250" Description="介绍" />
      <Column Name="Link" DataType="String" Length="250" Description="页面连接地址" />
      <Column Name="PId" DataType="Int32" Description="上级ID" />
      <Column Name="Level" DataType="Int32" Description="级别" />
      <Column Name="Location" DataType="String" Length="100" Description="路径" />
      <Column Name="IsHide" DataType="Int32" Description="是否隐藏" />
      <Column Name="Rank" DataType="Int32" Description="排序" />
      <Column Name="Icon" DataType="String" Length="100" Description="图标" />
      <Column Name="ClassName" DataType="String" Description="样式名称" />
    </Columns>
  </Table>
  <Table Name="AdminMenuEvent" Description="后台菜单对应的事件权限" DbType="SqlServer">
    <Columns>
      <Column Name="Id" DataType="Int32" Identity="True" PrimaryKey="True" Description="编号" />
      <Column Name="MenuId" DataType="Int32" Description="菜单ID" />
      <Column Name="MenuKey" DataType="String" Master="True" Length="100" Description="菜单key" />
      <Column Name="EventId" DataType="Int32" Description="事件ID" />
      <Column Name="EventKey" DataType="String" Master="True" Length="100" Description="事件key" />
      <Column Name="EventName" DataType="String" Length="100" Description="事件名称" />
    </Columns>
  </Table>
  <Table Name="Config" Description="系统配置" DbType="SqlServer">
    <Columns>
      <Column Name="Id" DataType="Int32" Identity="True" PrimaryKey="True" Description="编号" />
      <Column Name="SiteName" DataType="String" Length="250" Description="站点名称" />
      <Column Name="SiteUrl" DataType="String" Description="站点URL" />
      <Column Name="SiteLogo" DataType="String" Length="250" Description="站点LOGO" />
      <Column Name="Icp" DataType="String" Description="ICP备案" />
      <Column Name="SiteEmail" DataType="String" Length="100" Description="联系我们Email" />
      <Column Name="SiteTel" DataType="String" Description="网站电话" />
      <Column Name="Copyright" DataType="String" Length="-1" Description="版权所有" />
      <Column Name="IsCloseSite" DataType="Boolean" Description="是否关闭网站" />
      <Column Name="CloseReason" DataType="String" Length="-1" Description="关闭原因" />
      <Column Name="CountScript" DataType="String" Length="-1" Description="统计代码" />
      <Column Name="WeiboQRCode" DataType="String" Length="250" Description="微博二维码" />
      <Column Name="WinxinQRCode" DataType="String" Length="250" Description="微信二维码" />
      <Column Name="Keyword" DataType="String" Length="250" Description="关键字" />
      <Column Name="Description" DataType="String" Length="250" Description="描述" />
      <Column Name="IndexTitle" DataType="String" Length="250" Description="首页标题" />
      <Column Name="IsRewrite" DataType="Int32" Description="是否URL地址重写" />
      <Column Name="SearchMinTime" DataType="Int32" Description="搜索最小时间间距 秒" />
      <Column Name="OnlineQQ" DataType="String" Length="250" Description="在线QQ" />
      <Column Name="OnlineSkype" DataType="String" Length="250" Description="在线Skype" />
      <Column Name="OnlineWangWang" DataType="String" Length="250" Description="在线阿里旺旺" />
      <Column Name="SkinName" DataType="String" Description="站点URL" />
      <Column Name="OfficialName" DataType="String" Description="公众号名称" />
      <Column Name="OfficialDecsription" DataType="String" Length="250" Description="公众号介绍" />
      <Column Name="OfficialOriginalId" DataType="String" Length="100" Description="公众号原始ID" />
      <Column Name="WexinAccount" DataType="String" Description="微信名称" />
      <Column Name="Token" DataType="String" Length="100" Description="Token" />
      <Column Name="AppId" DataType="String" Length="100" Description="AppId" />
      <Column Name="AppSecret" DataType="String" Length="100" Description="AppSecret" />
      <Column Name="FllowTipPageURL" DataType="String" Length="250" Description="引导关注素材地址" />
      <Column Name="OfficialType" DataType="Int32" Description="公众号类型：0普通订阅号  1普通服务号  2认证订阅号  3认证服务号 4企业号 5认证企业号" />
      <Column Name="EncodingAESKey" DataType="String" Length="250" Description="EncodingAESKey" />
      <Column Name="DEType" DataType="Int32" Description="解密方式0,明文" />
      <Column Name="OfficialQRCode" DataType="String" Length="250" Description="公众号二维码地址" />
      <Column Name="OfficialImg" DataType="String" Length="250" Description="公众号头像" />
      <Column Name="LastUpdateTime" DataType="DateTime" Description="最后更新时间" />
      <Column Name="LastCacheTime" DataType="DateTime" Description="最后缓存时间" />
      <Column Name="MCHId" DataType="String" Length="100" Description="微信商家MCHId" />
      <Column Name="MCHKey" DataType="String" Length="100" Description="微信商家key" />
      <Column Name="DefaultFare" DataType="Decimal" Description="默认运费" />
      <Column Name="MaxFreeFare" DataType="Decimal" Description="最大免运费金额" />
      <Column Name="WXAppId" DataType="String" Length="100" Description="微信小程序AppId" />
      <Column Name="WXAppSecret" DataType="String" Length="100" Description="微信小程序AppSecret" />
      <Column Name="IsResetData" DataType="Int32" Description="小程序首页是否显示清除数据按钮" />
    </Columns>
  </Table>
  <Table Name="OtherConfig" Description="其他配置" DbType="SqlServer">
    <Columns>
      <Column Name="Id" DataType="Int32" Identity="True" PrimaryKey="True" Description="编号" />
      <Column Name="ConfigName" DataType="String" Description="配置名称" />
      <Column Name="ConfigValue" DataType="String" Length="-1" Description="配置值 JSON" />
      <Column Name="LastUpdateTime" DataType="DateTime" Description="最后更新时间" />
    </Columns>
  </Table>
  <Table Name="AdsKind" Description="广告类别" DbType="SqlServer">
    <Columns>
      <Column Name="Id" DataType="Int32" Identity="True" PrimaryKey="True" Description="编号" />
      <Column Name="KindName" DataType="String" Description="广告类别名称" />
      <Column Name="KindInfo" DataType="String" Length="250" Description="简单说明" />
      <Column Name="Rank" DataType="Int32" Description="排序" />
    </Columns>
  </Table>
  <Table Name="Ads" Description="广告详情" DbType="SqlServer">
    <Columns>
      <Column Name="Id" DataType="Int32" Identity="True" PrimaryKey="True" Description="编号" />
      <Column Name="Title" DataType="String" Master="True" Length="100" Description="广告标题" />
      <Column Name="Content" DataType="String" Length="-1" Description="广告详情JSON" />
      <Column Name="KId" DataType="Int32" Description="分类ID" />
      <Column Name="TId" DataType="Int32" Description="广告代码类型：0代码、1文字广告、2图片广告、3Flash广告、4幻灯片广告、5漂浮广告、6对联浮动图片广告" />
      <Column Name="StartTime" DataType="DateTime" Description="起始时间" />
      <Column Name="EndTime" DataType="DateTime" Description="结束时间" />
      <Column Name="IsDisabled" DataType="Boolean" Description="是否禁用广告" />
      <Column Name="Sequence" DataType="Int32" Description="排序，默认999" />
    </Columns>
  </Table>
  <Table Name="LinkKind" Description="友情链接分类" DbType="SqlServer">
    <Columns>
      <Column Name="Id" DataType="Int32" Identity="True" PrimaryKey="True" Description="编号" />
      <Column Name="KindName" DataType="String" Description="类别名称" />
      <Column Name="KindInfo" DataType="String" Length="250" Description="简单说明" />
      <Column Name="Pic" DataType="String" Length="250" Description="分类图片" />
      <Column Name="Rank" DataType="Int32" Description="排序" />
    </Columns>
  </Table>
  <Table Name="ArticleCategory" Description="文章栏目" DbType="SqlServer">
    <Columns>
      <Column Name="Id" DataType="Int32" Identity="True" PrimaryKey="True" Description="编号" />
      <Column Name="KindName" DataType="String" Length="250" Description="栏目名称" />
      <Column Name="SubTitle" DataType="String" Length="250" Description="栏目副标题" />
      <Column Name="KindTitle" DataType="String" Length="250" Description="栏目标题，填写则在浏览器替换此标题" />
      <Column Name="Keyword" DataType="String" Length="250" Description="描述" />
      <Column Name="Description" DataType="String" Length="250" Description="介绍" />
      <Column Name="LinkURL" DataType="String" Length="250" Description="跳转链接" />
      <Column Name="TitleColor" DataType="String" Description="类别名称颜色" />
      <Column Name="TemplateFile" DataType="String" Length="250" Description="模板" />
      <Column Name="DetailTemplateFile" DataType="String" Length="250" Description="详情模板" />
      <Column Name="KindDomain" DataType="String" Length="250" Description="类别域名（保留）" />
      <Column Name="IsList" DataType="Int32" Description="是否为列表页面" />
      <Column Name="PageSize" DataType="Int32" Description="每页显示数量" />
      <Column Name="PId" DataType="Int32" Description="上级ID" />
      <Column Name="Level" DataType="Int32" Description="级别" />
      <Column Name="Location" DataType="String" Length="100" Description="路径" />
      <Column Name="IsHide" DataType="Int32" Description="是否隐藏" />
      <Column Name="IsLock" DataType="Int32" Description="是否锁定，不允许删除" />
      <Column Name="IsDel" DataType="Int32" Description="是否删除,已经删除到回收站" />
      <Column Name="IsComment" DataType="Int32" Description="是否允许评论" />
      <Column Name="IsMember" DataType="Int32" Description="是否会员栏目" />
      <Column Name="IsShowSubDetail" DataType="Int32" Description="是否显示下级栏目内容" />
      <Column Name="CatalogId" DataType="Int32" Description="模型ID" />
      <Column Name="Counts" DataType="Int32" Description="详情数量，缓存" />
      <Column Name="Rank" DataType="Int32" Description="排序" />
      <Column Name="Icon" DataType="String" Length="100" Description="图标" />
      <Column Name="ClassName" DataType="String" Description="样式名称" />
      <Column Name="BannerImg" DataType="String" Length="250" Description="banner图片" />
      <Column Name="KindInfo" DataType="String" Length="-1" Description="栏目详细介绍" />
      <Column Name="Pic" DataType="String" Length="250" Description="图片" />
      <Column Name="AdsId" DataType="Int32" Description="广告ID" />
      <Column Name="FilePath" DataType="String" Length="100" Description="目录路径" />
    </Columns>
  </Table>
  <Table Name="Article" Description="文章" DbType="SqlServer">
    <Columns>
      <Column Name="Id" DataType="Int32" Identity="True" PrimaryKey="True" Description="编号" />
      <Column Name="KId" DataType="Int32" Description="栏目ID" />
      <Column Name="Title" DataType="String" Master="True" Length="250" Description="标题" />
      <Column Name="SubTitle" DataType="String" Length="250" Description="副标题" />
      <Column Name="Content" DataType="String" Length="-1" Description="内容" />
      <Column Name="Keyword" DataType="String" Length="250" Description="描述" />
      <Column Name="Description" DataType="String" Length="250" Description="介绍" />
      <Column Name="LinkURL" DataType="String" Length="250" Description="跳转链接" />
      <Column Name="TitleColor" DataType="String" Description="类别名称颜色" />
      <Column Name="TemplateFile" DataType="String" Length="250" Description="模板" />
      <Column Name="IsRecommend" DataType="Int32" Description="是否推荐" />
      <Column Name="IsNew" DataType="Int32" Description="是否最新" />
      <Column Name="IsBest" DataType="Int32" Description="是否推荐" />
      <Column Name="IsHide" DataType="Int32" Description="是否隐藏" />
      <Column Name="IsLock" DataType="Int32" Description="是否锁定，不允许删除" />
      <Column Name="IsDel" DataType="Int32" Description="是否删除,已经删除到回收站" />
      <Column Name="IsTop" DataType="Int32" Description="是否置顶" />
      <Column Name="IsComment" DataType="Int32" Description="是否允许评论" />
      <Column Name="IsMember" DataType="Int32" Description="是否会员栏目" />
      <Column Name="Hits" DataType="Int32" Description="点击数量" />
      <Column Name="Sequence" DataType="Int32" Description="排序" />
      <Column Name="CommentCount" DataType="Int32" Description="评论数量" />
      <Column Name="Icon" DataType="String" Length="100" Description="图标" />
      <Column Name="ClassName" DataType="String" Description="样式名称" />
      <Column Name="BannerImg" DataType="String" Length="250" Description="banner图片" />
      <Column Name="Pic" DataType="String" Length="250" Description="图片" />
      <Column Name="AdsId" DataType="Int32" Description="广告ID" />
      <Column Name="Tags" DataType="String" Length="250" Description="TAG" />
      <Column Name="Origin" DataType="String" Length="250" Description="来源" />
      <Column Name="OriginURL" DataType="String" Length="250" Description="来源地址" />
      <Column Name="ItemImg" DataType="String" Length="-1" Description="更多图片" />
      <Column Name="AuthorId" DataType="Int32" Description="添加管理员ID" />
      <Column Name="AddTime" DataType="DateTime" Description="添加时间" />
      <Column Name="UpdateTime" DataType="DateTime" Description="时间" />
      <Column Name="Location" DataType="String" Length="100" Description="路径" />
      <Column Name="FilePath" DataType="String" Length="100" Description="存放目录" />
      <Column Name="FileName" DataType="String" Description="文件名称" />
    </Columns>
  </Table>
  <Table Name="Category" Description="商品栏目" DbType="SqlServer">
    <Columns>
      <Column Name="Id" DataType="Int32" Identity="True" PrimaryKey="True" Description="编号" />
      <Column Name="KindName" DataType="String" Length="250" Description="栏目名称" />
      <Column Name="SubTitle" DataType="String" Length="250" Description="栏目副标题" />
      <Column Name="KindTitle" DataType="String" Length="250" Description="栏目标题，填写则在浏览器替换此标题" />
      <Column Name="Keyword" DataType="String" Length="250" Description="描述" />
      <Column Name="Description" DataType="String" Length="250" Description="介绍" />
      <Column Name="LinkURL" DataType="String" Length="250" Description="跳转链接" />
      <Column Name="TitleColor" DataType="String" Description="类别名称颜色" />
      <Column Name="TemplateFile" DataType="String" Length="250" Description="模板" />
      <Column Name="DetailTemplateFile" DataType="String" Length="250" Description="详情模板" />
      <Column Name="KindDomain" DataType="String" Length="250" Description="类别域名（保留）" />
      <Column Name="IsList" DataType="Int32" Description="是否为列表页面" />
      <Column Name="PageSize" DataType="Int32" Description="每页显示数量" />
      <Column Name="PId" DataType="Int32" Description="上级ID" />
      <Column Name="Level" DataType="Int32" Description="级别" />
      <Column Name="Location" DataType="String" Length="100" Description="路径" />
      <Column Name="IsHide" DataType="Int32" Description="是否隐藏" />
      <Column Name="IsLock" DataType="Int32" Description="是否锁定，不允许删除" />
      <Column Name="IsDel" DataType="Int32" Description="是否删除,已经删除到回收站" />
      <Column Name="IsComment" DataType="Int32" Description="是否允许评论" />
      <Column Name="IsMember" DataType="Int32" Description="是否会员栏目" />
      <Column Name="IsShowSubDetail" DataType="Int32" Description="是否显示下级栏目内容" />
      <Column Name="CatalogId" DataType="Int32" Description="模型ID" />
      <Column Name="Counts" DataType="Int32" Description="详情数量，缓存" />
      <Column Name="Rank" DataType="Int32" Description="排序" />
      <Column Name="Icon" DataType="String" Length="100" Description="图标" />
      <Column Name="ClassName" DataType="String" Description="样式名称" />
      <Column Name="BannerImg" DataType="String" Length="250" Description="banner图片" />
      <Column Name="KindInfo" DataType="String" Length="-1" Description="栏目详细介绍" />
      <Column Name="Pic" DataType="String" Length="250" Description="图片" />
      <Column Name="AdsId" DataType="Int32" Description="广告ID" />
      <Column Name="FilePath" DataType="String" Length="100" Description="目录路径" />
    </Columns>
  </Table>
  <Table Name="Product" Description="商品" DbType="SqlServer">
    <Columns>
      <Column Name="Id" DataType="Int32" Identity="True" PrimaryKey="True" Description="编号" />
      <Column Name="KId" DataType="Int32" Description="栏目ID" />
      <Column Name="BId" DataType="Int32" Description="品牌ID" />
      <Column Name="ShopId" DataType="Int32" Description="店铺ID" />
      <Column Name="CId" DataType="Int32" Description="颜色ID" />
      <Column Name="SupportId" DataType="Int32" Description="供货商ID" />
      <Column Name="Title" DataType="String" Master="True" Length="250" Description="标题" />
      <Column Name="ItemNO" DataType="String" Description="编号" />
      <Column Name="SubTitle" DataType="String" Length="250" Description="副标题" />
      <Column Name="Unit" DataType="String" Length="250" Description="商品单位" />
      <Column Name="Spec" DataType="String" Length="250" Description="商品规格尺寸" />
      <Column Name="Color" DataType="String" Length="250" Description="颜色" />
      <Column Name="Weight" DataType="String" Description="重量" />
      <Column Name="Price" DataType="Decimal" Description="价格" />
      <Column Name="MarketPrice" DataType="Decimal" Description="市场价格" />
      <Column Name="SpecialPrice" DataType="Decimal" Description="特价，如有特价，以特价为准" />
      <Column Name="Fare" DataType="Decimal" Description="运费" />
      <Column Name="Discount" DataType="Decimal" Description="折扣" />
      <Column Name="Material" DataType="String" Length="250" Description="材料" />
      <Column Name="Front" DataType="String" Length="250" Description="封面" />
      <Column Name="Credits" DataType="Int32" Description="积分" />
      <Column Name="Stock" DataType="Int32" Description="库存" />
      <Column Name="WarnStock" DataType="Int32" Description="警告库存" />
      <Column Name="IsSubProduct" DataType="Int32" Description="是否为子商品" />
      <Column Name="PPId" DataType="Int32" Description="父商品ID。如果为子商品，则需要填写父商品ID。实现多颜色功能" />
      <Column Name="Content" DataType="String" Length="-1" Description="内容" />
      <Column Name="Parameters" DataType="String" Length="-1" Description="商品参数" />
      <Column Name="Keyword" DataType="String" Length="250" Description="描述" />
      <Column Name="Description" DataType="String" Length="250" Description="介绍" />
      <Column Name="LinkURL" DataType="String" Length="250" Description="跳转链接" />
      <Column Name="TitleColor" DataType="String" Description="类别名称颜色" />
      <Column Name="TemplateFile" DataType="String" Length="250" Description="模板" />
      <Column Name="IsRecommend" DataType="Int32" Description="是否推荐" />
      <Column Name="IsHide" DataType="Int32" Description="是否隐藏" />
      <Column Name="IsLock" DataType="Int32" Description="是否锁定，不允许删除" />
      <Column Name="IsDel" DataType="Int32" Description="是否删除,已经删除到回收站" />
      <Column Name="IsTop" DataType="Int32" Description="是否置顶" />
      <Column Name="IsBest" DataType="Int32" Description="是否精华" />
      <Column Name="IsComment" DataType="Int32" Description="是否允许评论" />
      <Column Name="IsMember" DataType="Int32" Description="是否会员栏目" />
      <Column Name="IsNew" DataType="Int32" Description="是否新品" />
      <Column Name="IsSpecial" DataType="Int32" Description="是否特价" />
      <Column Name="IsPromote" DataType="Int32" Description="是否促销" />
      <Column Name="IsHotSales" DataType="Int32" Description="是否热销" />
      <Column Name="IsBreakup" DataType="Int32" Description="是否缺货" />
      <Column Name="IsShelves" DataType="Int32" Description="是否下架" />
      <Column Name="IsVerify" DataType="Int32" Description="是否审核，1为已经审核前台显示" />
      <Column Name="Hits" DataType="Int32" Description="点击数量" />
      <Column Name="IsGift" DataType="Int32" Description="是否为礼品商品" />
      <Column Name="IsPart" DataType="Int32" Description="是否为配件" />
      <Column Name="Sequence" DataType="Int32" Description="排序" />
      <Column Name="CommentCount" DataType="Int32" Description="评论数量" />
      <Column Name="Icon" DataType="String" Length="100" Description="图标" />
      <Column Name="ClassName" DataType="String" Description="样式名称" />
      <Column Name="BannerImg" DataType="String" Length="250" Description="banner图片" />
      <Column Name="Pic" DataType="String" Length="250" Description="图片" />
      <Column Name="AdsId" DataType="Int32" Description="广告ID" />
      <Column Name="Tags" DataType="String" Length="250" Description="TAG" />
      <Column Name="ItemImg" DataType="String" Length="-1" Description="更多图片" />
      <Column Name="Service" DataType="String" Length="-1" Description="售后服务" />
      <Column Name="AuthorId" DataType="Int32" Description="添加管理员ID" />
      <Column Name="AddTime" DataType="DateTime" Description="添加时间" />
      <Column Name="UpdateTime" DataType="DateTime" Description="时间" />
      <Column Name="Location" DataType="String" Length="100" Description="路径" />
      <Column Name="FilePath" DataType="String" Length="100" Description="存放目录" />
      <Column Name="FileName" DataType="String" Description="文件名称" />
    </Columns>
  </Table>
  <Table Name="Link" Description="友情连接详情" DbType="SqlServer">
    <Columns>
      <Column Name="Id" DataType="Int32" Identity="True" PrimaryKey="True" Description="编号" />
      <Column Name="KId" DataType="Int32" Description="分类ID" />
      <Column Name="Title" DataType="String" Master="True" Length="250" Description="站点标题" />
      <Column Name="LinkURL" DataType="String" Length="250" Description="站点连接" />
      <Column Name="Info" DataType="String" Length="250" Description="介绍" />
      <Column Name="Logo" DataType="String" Length="250" Description="站点LOGO" />
      <Column Name="IsHide" DataType="Boolean" Description="是否隐藏友情链接" />
      <Column Name="Sequence" DataType="Int32" Description="排序，默认999" />
    </Columns>
  </Table>
  <Table Name="ShoppingCart" Description="购物车" DbType="SqlServer">
    <Columns>
      <Column Name="Id" DataType="Int32" Identity="True" PrimaryKey="True" Description="编号" />
      <Column Name="UId" DataType="Int32" Description="用户ID" />
      <Column Name="Guid" DataType="String" Description="唯一GUID，没登录用户使用" />
      <Column Name="Details" DataType="String" Length="-1" Description="购物车内容，JOSN" />
      <Column Name="AddTime" DataType="DateTime" Description="加入购物车时间" />
      <Column Name="UpdateTime" DataType="DateTime" Description="最后更新时间" />
    </Columns>
  </Table>
  <Table Name="MemberLog" Description="用户日志表" DbType="SqlServer">
    <Columns>
      <Column Name="Id" DataType="Int32" Identity="True" PrimaryKey="True" Master="True" Description="编号" />
      <Column Name="UId" DataType="Int32" Description="管理员ID" />
      <Column Name="Guid" DataType="String" Description="唯一ID" />
      <Column Name="UserName" DataType="String" Length="20" Description="用户名" />
      <Column Name="PassWord" DataType="String" Description="密码" />
      <Column Name="LoginTime" DataType="DateTime" Description="登录时间" />
      <Column Name="LoginIP" DataType="String" Length="20" Description="登录IP" />
      <Column Name="IsLoginOK" DataType="Int32" Description="是否登录成功" />
      <Column Name="Actions" DataType="String" Length="-1" Description="记录" />
      <Column Name="LastUpdateTime" DataType="DateTime" Description="登录时间" />
    </Columns>
  </Table>
  <Table Name="Order" Description="订单" DbType="SqlServer">
    <Columns>
      <Column Name="Id" DataType="Int32" Identity="True" PrimaryKey="True" Master="True" Description="编号" />
      <Column Name="OrderNum" DataType="String" Description="订单号" />
      <Column Name="UId" DataType="Int32" Description="用户ID" />
      <Column Name="UserName" DataType="String" Description="下单用户名" />
      <Column Name="ShopId" DataType="Int32" Description="商户ID" />
      <Column Name="Credit" DataType="Int32" Description="积分" />
      <Column Name="TotalQty" DataType="Int32" Description="总数量" />
      <Column Name="TotalPrice" DataType="Decimal" Description="总价格" />
      <Column Name="Discount" DataType="Decimal" Description="折扣" />
      <Column Name="Fare" DataType="Decimal" Description="运费" />
      <Column Name="TotalTax" DataType="Decimal" Description="税" />
      <Column Name="TotalPay" DataType="Decimal" Description="总支付价格" />
      <Column Name="BackCredits" DataType="Int32" Description="返现积分" />
      <Column Name="RealName" DataType="String" Description="姓名" />
      <Column Name="Country" DataType="String" Description="国家" />
      <Column Name="Province" DataType="String" Description="省份" />
      <Column Name="City" DataType="String" Description="城市" />
      <Column Name="District" DataType="String" Description="区" />
      <Column Name="Address" DataType="String" Length="250" Description="详细地址" />
      <Column Name="PostCode" DataType="String" Length="20" Description="邮编" />
      <Column Name="Tel" DataType="String" Length="20" Description="手机" />
      <Column Name="Mobile" DataType="String" Length="20" Description="手机" />
      <Column Name="Email" DataType="String" Length="100" Description="邮箱" />
      <Column Name="Notes" DataType="String" Length="250" Description="备注" />
      <Column Name="AdminNotes" DataType="String" Length="250" Description="管理员备注" />
      <Column Name="Pic" DataType="String" Length="-1" Description="图片" />
      <Column Name="DeliverId" DataType="Int32" Description="配送方式ID" />
      <Column Name="DeliverType" DataType="String" Description="配送方式名称" />
      <Column Name="DeliverNO" DataType="String" Description="运单号" />
      <Column Name="DeliverNotes" DataType="String" Length="250" Description="配送备注" />
      <Column Name="PayId" DataType="Int32" Description="支付方式ID" />
      <Column Name="PayType" DataType="String" Description="付款方式" />
      <Column Name="PayTypeNotes" DataType="String" Length="250" Description="支付备注" />
      <Column Name="OrderStatus" DataType="String" Description="订单状态：未确认、已确认、已完成、已取消" />
      <Column Name="PaymentStatus" DataType="String" Description="支付状态：未支付、已支付、已退款" />
      <Column Name="DeliverStatus" DataType="String" Description="配送状态：未配送、配货中、已配送、已收到、退货中、已退货" />
      <Column Name="AddTime" DataType="DateTime" Description="添加时间" />
      <Column Name="Ip" DataType="String" Length="20" Description="下单IP" />
      <Column Name="IsInvoice" DataType="Int32" Description="是否需要发票" />
      <Column Name="InvoiceCompanyName" DataType="String" Description="抬头" />
      <Column Name="InvoiceCompanyID" DataType="String" Length="100" Description="纳税人识别号" />
      <Column Name="InvoiceType" DataType="String" Description="发票内容" />
      <Column Name="InvoiceNote" DataType="String" Length="250" Description="发票备注" />
      <Column Name="IsRead" DataType="Int32" Description="是否未读" />
      <Column Name="IsEnd" DataType="Int32" Description="是否结束" />
      <Column Name="EndTime" DataType="DateTime" Description="结束时间" />
      <Column Name="IsOk" DataType="Int32" Description="订单是否顺利完成" />
      <Column Name="IsComment" DataType="Int32" Description="订单已经评论" />
      <Column Name="Flag1" DataType="String" Length="200" Description="预留字段1" />
      <Column Name="Flag2" DataType="String" Length="200" Description="预留字段2" />
      <Column Name="Flag3" DataType="String" Length="200" Description="预留字段3" />
      <Column Name="Title" DataType="String" Length="200" Description="订单名称" />
      <Column Name="LastModTime" DataType="DateTime" Description="最后操作时间" />
      <Column Name="OrderType" DataType="Int32" Description="订单类型，0为商品订单" />
      <Column Name="MyType" DataType="Int32" Description="系统类型" />
      <Column Name="OutTradeNo" DataType="String" Length="100" Description="支付成功流水号" />
    </Columns>
  </Table>
  <Table Name="OrderDetail" Description="订单详情" DbType="SqlServer">
    <Columns>
      <Column Name="Id" DataType="Int32" Identity="True" PrimaryKey="True" Master="True" Description="编号" />
      <Column Name="OrderId" DataType="Int32" Description="订单ID" />
      <Column Name="OrderNum" DataType="String" Description="订单号" />
      <Column Name="ShopId" DataType="Int32" Description="商户ID" />
      <Column Name="UId" DataType="Int32" Description="用户ID" />
      <Column Name="PId" DataType="Int32" Description="商品ID" />
      <Column Name="TypeId" DataType="Int32" Description="类型ID" />
      <Column Name="PriceId" DataType="Int32" Description="价格ID" />
      <Column Name="Title" DataType="String" Length="250" Description="商品名称" />
      <Column Name="Pic" DataType="String" Length="250" Description="商品名称" />
      <Column Name="Attr" DataType="String" Length="250" Description="商品属性" />
      <Column Name="Color" DataType="String" Description="商品颜色" />
      <Column Name="Spec" DataType="String" Description="规格" />
      <Column Name="ItemNO" DataType="String" Description="编号" />
      <Column Name="Qty" DataType="Int32" Description="数量" />
      <Column Name="Price" DataType="Decimal" Description="商品价格" />
      <Column Name="MarketPrice" DataType="Decimal" Description="商品市场价格" />
      <Column Name="SpecialPrice" DataType="Decimal" Description="商品特价" />
      <Column Name="Discount" DataType="Decimal" Description="商品优惠" />
      <Column Name="Tax" DataType="Decimal" Description="商品税" />
      <Column Name="Credit" DataType="Int32" Description="积分" />
      <Column Name="BackCredits" DataType="Int32" Description="返现积分" />
      <Column Name="IsOK" DataType="Int32" Description="是否完成" />
      <Column Name="IsComment" DataType="Int32" Description="是否已经评论" />
      <Column Name="AddTime" DataType="DateTime" Description="添加时间" />
      <Column Name="CheckInDate" DataType="DateTime" Description="入住日期" />
      <Column Name="LeaveDate" DataType="DateTime" Description="离开日期" />
      <Column Name="MyType" DataType="Int32" Description="系统类型" />
    </Columns>
  </Table>
  <Table Name="OrderLog" Description="订单日志" DbType="SqlServer">
    <Columns>
      <Column Name="Id" DataType="Int32" Identity="True" PrimaryKey="True" Master="True" Description="编号" />
      <Column Name="OrderId" DataType="Int32" Description="订单ID" />
      <Column Name="OrderNum" DataType="String" Description="订单号" />
      <Column Name="Actions" DataType="String" Length="200" Description="日志记录" />
      <Column Name="UId" DataType="Int32" Description="用户ID" />
      <Column Name="AddTime" DataType="DateTime" Description="添加时间" />
    </Columns>
  </Table>
  <Table Name="OnlinePayOrder" Description="在线支付订单" DbType="SqlServer">
    <Columns>
      <Column Name="Id" DataType="Int32" Identity="True" PrimaryKey="True" Master="True" Description="编号" />
      <Column Name="PayOrderNum" DataType="String" Description="在线支付订单号，唯一" />
      <Column Name="OrderId" DataType="Int32" Description="订单ID" />
      <Column Name="OrderNum" DataType="String" Description="订单号" />
      <Column Name="PayId" DataType="Int32" Description="支付方式ID" />
      <Column Name="PayType" DataType="String" Description="付款方式" />
      <Column Name="PayTypeNotes" DataType="String" Length="250" Description="支付备注" />
      <Column Name="Actions" DataType="String" Length="200" Description="日志记录" />
      <Column Name="UId" DataType="Int32" Description="用户ID" />
      <Column Name="UserName" DataType="String" Description="用户名" />
      <Column Name="TotalQty" DataType="Int32" Description="总数量" />
      <Column Name="TotalPrice" DataType="Decimal" Description="总价格" />
      <Column Name="PaymentStatus" DataType="String" Description="支付状态：未支付、已支付、已退款" />
      <Column Name="PaymentNotes" DataType="String" Length="250" Description="支付备注" />
      <Column Name="IsOK" DataType="Int32" Description="是否完成" />
      <Column Name="Ip" DataType="String" Length="20" Description="下单IP" />
      <Column Name="AddTime" DataType="DateTime" Description="添加时间" />
      <Column Name="ReceiveTime" DataType="DateTime" Description="回传时间" />
      <Column Name="TypeId" DataType="Int32" Description="支付的类型" />
      <Column Name="MyType" DataType="Int32" Description="系统类型" />
      <Column Name="Title" DataType="String" Description="订单标题" />
      <Column Name="OutTradeNo" DataType="String" Length="100" Description="支付成功流水号" />
    </Columns>
  </Table>
  <Table Name="GuestbookCategory" Description="留言分类" DbType="SqlServer">
    <Columns>
      <Column Name="Id" DataType="Int32" Identity="True" PrimaryKey="True" Description="编号" />
      <Column Name="KindName" DataType="String" Length="250" Description="栏目名称" />
      <Column Name="SubTitle" DataType="String" Length="250" Description="栏目副标题" />
      <Column Name="KindTitle" DataType="String" Length="250" Description="栏目标题，填写则在浏览器替换此标题" />
      <Column Name="Keyword" DataType="String" Length="250" Description="描述" />
      <Column Name="Description" DataType="String" Length="250" Description="介绍" />
      <Column Name="LinkURL" DataType="String" Length="250" Description="跳转链接" />
      <Column Name="TitleColor" DataType="String" Description="类别名称颜色" />
      <Column Name="TemplateFile" DataType="String" Length="250" Description="模板" />
      <Column Name="DetailTemplateFile" DataType="String" Length="250" Description="详情模板" />
      <Column Name="KindDomain" DataType="String" Length="250" Description="类别域名（保留）" />
      <Column Name="IsList" DataType="Int32" Description="是否为列表页面" />
      <Column Name="PageSize" DataType="Int32" Description="每页显示数量" />
      <Column Name="PId" DataType="Int32" Description="上级ID" />
      <Column Name="Level" DataType="Int32" Description="级别" />
      <Column Name="Location" DataType="String" Length="100" Description="路径" />
      <Column Name="IsHide" DataType="Int32" Description="是否隐藏" />
      <Column Name="IsLock" DataType="Int32" Description="是否锁定，不允许删除" />
      <Column Name="IsDel" DataType="Int32" Description="是否删除,已经删除到回收站" />
      <Column Name="IsComment" DataType="Int32" Description="是否允许评论" />
      <Column Name="IsMember" DataType="Int32" Description="是否会员栏目" />
      <Column Name="IsShowSubDetail" DataType="Int32" Description="是否显示下级栏目内容" />
      <Column Name="CatalogId" DataType="Int32" Description="模型ID" />
      <Column Name="Counts" DataType="Int32" Description="详情数量，缓存" />
      <Column Name="Rank" DataType="Int32" Description="排序" />
      <Column Name="Icon" DataType="String" Length="100" Description="图标" />
      <Column Name="ClassName" DataType="String" Description="样式名称" />
      <Column Name="BannerImg" DataType="String" Length="250" Description="banner图片" />
      <Column Name="KindInfo" DataType="String" Length="-1" Description="栏目详细介绍" />
      <Column Name="Pic" DataType="String" Length="250" Description="图片" />
      <Column Name="AdsId" DataType="Int32" Description="广告ID" />
    </Columns>
  </Table>
  <Table Name="Guestbook" Description="留言详情" DbType="SqlServer">
    <Columns>
      <Column Name="Id" DataType="Int32" Identity="True" PrimaryKey="True" Description="编号" />
      <Column Name="KId" DataType="Int32" Description="分类ID" />
      <Column Name="UId" DataType="Int32" Description="用户ID" />
      <Column Name="Title" DataType="String" Master="True" Length="250" Description="留言标题" />
      <Column Name="Content" DataType="String" Length="-1" Description="详细介绍" />
      <Column Name="AddTime" DataType="DateTime" Description="添加时间" />
      <Column Name="IsVerify" DataType="Int32" Description="是否审核通过" />
      <Column Name="IsRead" DataType="Int32" Description="是否阅读" />
      <Column Name="IsDel" DataType="Int32" Description="是否删除,已经删除到回收站" />
      <Column Name="Ip" DataType="String" Length="20" Description="用户IP" />
      <Column Name="Email" DataType="String" Length="100" Description="邮箱" />
      <Column Name="Tel" DataType="String" Description="电话" />
      <Column Name="Qq" DataType="String" Length="20" Description="QQ" />
      <Column Name="Skype" DataType="String" Length="100" Description="Skype" />
      <Column Name="HomePage" DataType="String" Length="250" Description="主页" />
      <Column Name="Address" DataType="String" Length="250" Description="地址" />
      <Column Name="Company" DataType="String" Length="250" Description="公司" />
      <Column Name="ReplyTitle" DataType="String" Length="250" Description="回复标题" />
      <Column Name="ReplyContent" DataType="String" Length="-1" Description="回复的详情" />
      <Column Name="ReplyAddTime" DataType="DateTime" Description="回复时间" />
      <Column Name="ReplyIP" DataType="String" Length="20" Description="用户回复IP" />
      <Column Name="ReplyAdminId" DataType="Int32" Description="用户的管理员ID" />
      <Column Name="ReplyNickName" DataType="String" Length="20" Description="回复者昵称" />
    </Columns>
  </Table>
  <Table Name="MemberRoles" Description="用户角色" DbType="SqlServer">
    <Columns>
      <Column Name="Id" DataType="Int32" Identity="True" PrimaryKey="True" Description="编号" />
      <Column Name="RoleName" DataType="String" Master="True" Description="角色名称" />
      <Column Name="RoleDescription" DataType="String" Master="True" Length="250" Description="角色简单介绍" />
      <Column Name="Stars" DataType="Int32" Description="星级" />
      <Column Name="NotAllowDel" DataType="Int32" Description="是否不允许删除" />
      <Column Name="Rank" DataType="Int32" Description="排序" />
      <Column Name="Color" DataType="String" Master="True" Length="20" Description="颜色" />
      <Column Name="CashBack" DataType="Decimal" Description="返现百分比" />
      <Column Name="ParentCashBack" DataType="Decimal" Description="父级返现百分比" />
      <Column Name="GrandfatherCashBack" DataType="Decimal" Description="爷级返现百分比" />
      <Column Name="IsDefault" DataType="Int32" Description="是否是默认角色" />
      <Column Name="IsHalved" DataType="Int32" Description="超过级别是否减半" />
      <Column Name="HalvedParentCashBack" DataType="Decimal" Description="超过级别父级返现百分比" />
      <Column Name="HalvedGrandfatherCashBack" DataType="Decimal" Description="超过级别爷级返现百分比" />
      <Column Name="YearsPerformance" DataType="Decimal" Description="年业务量" />
      <Column Name="IsSellers" DataType="Int32" Description="是否是分销商" />
      <Column Name="JoinPrice" DataType="Decimal" Description="加入分销商价格" />
    </Columns>
  </Table>
  <Table Name="Member" Description="用户" DbType="SqlServer">
    <Columns>
      <Column Name="Id" DataType="Int32" Identity="True" PrimaryKey="True" Description="编号" />
      <Column Name="UserName" DataType="String" Master="True" Length="20" Description="用户名" />
      <Column Name="PassWord" DataType="String" Description="密码" />
      <Column Name="Salt" DataType="String" Length="20" Description="盐值" />
      <Column Name="RealName" DataType="String" Length="20" Description="姓名" />
      <Column Name="Tel" DataType="String" Length="20" Description="手机" />
      <Column Name="Email" DataType="String" Master="True" Length="100" Description="邮件" />
      <Column Name="RoleId" DataType="Int32" Master="True" Description="会员组，代理级别" />
      <Column Name="LastLoginTime" DataType="DateTime" Description="最后登录时间" />
      <Column Name="LastLoginIP" DataType="String" Length="20" Description="上次登录IP" />
      <Column Name="ThisLoginTime" DataType="DateTime" Description="本次登录时间" />
      <Column Name="ThisLoginIP" DataType="String" Length="20" Description="本次登录IP" />
      <Column Name="IsLock" DataType="Int32" Description="是否是锁定" />
      <Column Name="Nickname" DataType="String" Length="200" Description="昵称" />
      <Column Name="UserImg" DataType="String" Length="250" Description="头像" />
      <Column Name="Sex" DataType="Int32" Description="性别 0 保密 1 男 2女" />
      <Column Name="Birthday" DataType="DateTime" Description="生日" />
      <Column Name="Phone" DataType="String" Length="20" Description="电话" />
      <Column Name="Fax" DataType="String" Length="20" Description="传真" />
      <Column Name="Qq" DataType="String" Length="20" Description="QQ" />
      <Column Name="Weixin" DataType="String" Description="微信" />
      <Column Name="Alipay" DataType="String" Description="支付宝" />
      <Column Name="Skype" DataType="String" Length="100" Description="skype" />
      <Column Name="Homepage" DataType="String" Length="100" Description="主页" />
      <Column Name="Company" DataType="String" Length="100" Description="公司" />
      <Column Name="Idno" DataType="String" Length="20" Description="身份证" />
      <Column Name="Country" DataType="String" Description="国家" />
      <Column Name="Province" DataType="String" Description="省" />
      <Column Name="City" DataType="String" Description="市" />
      <Column Name="District" DataType="String" Description="区" />
      <Column Name="Address" DataType="String" Length="250" Description="详细地址" />
      <Column Name="Postcode" DataType="String" Length="20" Description="邮政编码" />
      <Column Name="RegIP" DataType="String" Length="20" Description="注册IP" />
      <Column Name="RegTime" DataType="DateTime" Description="注册时间" />
      <Column Name="LoginCount" DataType="Int32" Description="登录次数" />
      <Column Name="RndNum" DataType="String" Description="随机字符" />
      <Column Name="RePassWordTime" DataType="DateTime" Description="找回密码时间" />
      <Column Name="Question" DataType="String" Description="保密问题" />
      <Column Name="Answer" DataType="String" Description="保密答案" />
      <Column Name="Balance" DataType="Decimal" Description="可用余额" />
      <Column Name="GiftBalance" DataType="Decimal" Description="赠送余额" />
      <Column Name="Rebate" DataType="Decimal" Description="返利，分销提成" />
      <Column Name="Bank" DataType="String" Description="银行" />
      <Column Name="BankCardNO" DataType="String" Description="银行卡号" />
      <Column Name="BankBranch" DataType="String" Description="支行名称" />
      <Column Name="BankRealname" DataType="String" Description="银行卡姓名" />
      <Column Name="YearsPerformance" DataType="Decimal" Description="年业务量" />
      <Column Name="ExtCredits1" DataType="Decimal" Description="备用积分1" />
      <Column Name="ExtCredits2" DataType="Decimal" Description="备用积分2" />
      <Column Name="ExtCredits3" DataType="Decimal" Description="备用积分3" />
      <Column Name="ExtCredits4" DataType="Decimal" Description="备用积分4" />
      <Column Name="ExtCredits5" DataType="Decimal" Description="备用积分5" />
      <Column Name="TotalCredits" DataType="Decimal" Description="总积分" />
      <Column Name="Parent" DataType="Int32" Description="父级用户ID" />
      <Column Name="Grandfather" DataType="Int32" Description="爷级用户ID" />
      <Column Name="IsSellers" DataType="Int32" Description="是否是分销商" />
      <Column Name="IsVerifySellers" DataType="Int32" Description="是否已经认证的分销商，缴纳费用" />
      <Column Name="WeixinOpenId" DataType="String" Length="100" Description="微信公众号OpenId" />
      <Column Name="WeixinAppOpenId" DataType="String" Length="100" Description="微信OpenId" />
      <Column Name="QQOpenId" DataType="String" Length="100" Description="QQ OpenId" />
      <Column Name="WeiboOpenId" DataType="String" Length="100" Description="微博OpenId" />
    </Columns>
  </Table>
  <Table Name="MemberAddress" Description="用户地址" DbType="SqlServer">
    <Columns>
      <Column Name="Id" DataType="Int32" Identity="True" PrimaryKey="True" Description="编号" />
      <Column Name="UId" DataType="Int32" Master="True" Description="用户ID" />
      <Column Name="RealName" DataType="String" Length="20" Description="姓名" />
      <Column Name="Tel" DataType="String" Length="20" Description="手机" />
      <Column Name="Email" DataType="String" Length="100" Description="邮件" />
      <Column Name="IsDefault" DataType="Boolean" Description="是否是默认" />
      <Column Name="Phone" DataType="String" Length="20" Description="电话" />
      <Column Name="Company" DataType="String" Length="100" Description="公司" />
      <Column Name="Country" DataType="String" Description="国家" />
      <Column Name="Province" DataType="String" Description="省" />
      <Column Name="City" DataType="String" Description="市" />
      <Column Name="District" DataType="String" Description="区" />
      <Column Name="Address" DataType="String" Length="250" Description="详细地址" />
      <Column Name="Postcode" DataType="String" Length="20" Description="邮政编码" />
      <Column Name="AddTime" DataType="DateTime" Description="添加时间" />
      <Column Name="UpdateTime" DataType="DateTime" Description="更新时间" />
      <Column Name="Rank" DataType="Int32" Description="排序" />
    </Columns>
  </Table>
  <Table Name="BalanceChangeLog" Description="用户余额变化记录" DbType="SqlServer">
    <Columns>
      <Column Name="Id" DataType="Int32" Identity="True" PrimaryKey="True" Description="编号" />
      <Column Name="UId" DataType="Int32" Master="True" Description="用户ID" />
      <Column Name="AdminId" DataType="Int32" Description="管理员ID" />
      <Column Name="UserName" DataType="String" Master="True" Length="20" Description="用户名" />
      <Column Name="AddTime" DataType="DateTime" Description="时间" />
      <Column Name="Ip" DataType="String" Length="20" Description="登录IP" />
      <Column Name="Actions" DataType="String" Master="True" Length="100" Description="记录" />
      <Column Name="Reward" DataType="Decimal" Description="总积分" />
      <Column Name="BeforChange" DataType="Decimal" Description="总积分" />
      <Column Name="AfterChange" DataType="Decimal" Description="总积分" />
      <Column Name="LogDetails" DataType="String" Master="True" Length="250" Description="详细记录" />
      <Column Name="TypeId" DataType="Int32" Description="类型 0 充值 1 购买 2 赠送 3 退款 4 分销提成" />
      <Column Name="OrderId" DataType="Int32" Description="订单ID" />
      <Column Name="OrderNum" DataType="String" Master="True" Description="订单号" />
    </Columns>
  </Table>
  <Table Name="RebateChangeLog" Description="用户返现余额变化记录" DbType="SqlServer">
    <Columns>
      <Column Name="Id" DataType="Int32" Identity="True" PrimaryKey="True" Description="编号" />
      <Column Name="UId" DataType="Int32" Description="用户ID" />
      <Column Name="AdminId" DataType="Int32" Description="管理员ID" />
      <Column Name="UserName" DataType="String" Length="200" Description="用户名" />
      <Column Name="AddTime" DataType="DateTime" Description="时间" />
      <Column Name="Ip" DataType="String" Length="20" Description="登录IP" />
      <Column Name="Actions" DataType="String" Master="True" Length="100" Description="记录" />
      <Column Name="Reward" DataType="Decimal" Description="返现、扣除金额" />
      <Column Name="BeforChange" DataType="Decimal" Description="变化前" />
      <Column Name="AfterChange" DataType="Decimal" Description="变化后" />
      <Column Name="LogDetails" DataType="String" Master="True" Length="250" Description="详细记录" />
      <Column Name="TypeId" DataType="Int32" Description="类型 0 充值 1 购买 2 赠送 3 退款 4 分销提成" />
      <Column Name="MyType" DataType="Int32" Description="消费类型，见MyType" />
      <Column Name="OrderId" DataType="Int32" Description="订单ID" />
      <Column Name="OrderNum" DataType="String" Master="True" Description="订单号" />
    </Columns>
  </Table>
  <Table Name="GuestbookCategory" Description="留言分类" DbType="SqlServer">
    <Columns>
      <Column Name="Id" DataType="Int32" Identity="True" PrimaryKey="True" Description="编号" />
      <Column Name="KindName" DataType="String" Description="类别名称" />
      <Column Name="KindInfo" DataType="String" Length="250" Description="简单说明" />
      <Column Name="Pic" DataType="String" Length="250" Description="分类图片" />
      <Column Name="Rank" DataType="Int32" Description="排序" />
    </Columns>
  </Table>
  <Table Name="Guestbook" Description="留言详情" DbType="SqlServer">
    <Columns>
      <Column Name="Id" DataType="Int32" Identity="True" PrimaryKey="True" Description="编号" />
      <Column Name="KId" DataType="Int32" Description="分类ID" />
      <Column Name="UId" DataType="Int32" Description="用户ID" />
      <Column Name="Title" DataType="String" Master="True" Length="250" Description="留言标题" />
      <Column Name="Content" DataType="String" Length="-1" Description="详细介绍" />
      <Column Name="AddTime" DataType="DateTime" Description="添加时间" />
      <Column Name="IsVerify" DataType="Int32" Description="是否审核通过" />
      <Column Name="IsRead" DataType="Int32" Description="是否阅读" />
      <Column Name="IsDel" DataType="Int32" Description="是否删除,已经删除到回收站" />
      <Column Name="Ip" DataType="String" Length="20" Description="用户IP" />
      <Column Name="Nickname" DataType="String" Description="昵称" />
      <Column Name="Email" DataType="String" Length="100" Description="邮箱" />
      <Column Name="Tel" DataType="String" Description="电话" />
      <Column Name="Qq" DataType="String" Length="20" Description="QQ" />
      <Column Name="Skype" DataType="String" Length="100" Description="Skype" />
      <Column Name="HomePage" DataType="String" Length="250" Description="主页" />
      <Column Name="Address" DataType="String" Length="250" Description="地址" />
      <Column Name="Company" DataType="String" Length="250" Description="公司" />
      <Column Name="ReplyTitle" DataType="String" Length="250" Description="回复标题" />
      <Column Name="ReplyContent" DataType="String" Length="-1" Description="回复的详情" />
      <Column Name="ReplyAddTime" DataType="DateTime" Description="回复时间" />
      <Column Name="ReplyIP" DataType="String" Length="20" Description="用户回复IP" />
      <Column Name="ReplyAdminId" DataType="Int32" Description="用户的管理员ID" />
      <Column Name="ReplyNickName" DataType="String" Length="20" Description="回复者昵称" />
    </Columns>
  </Table>
  <Table Name="Shop" Description="商家" DbType="SqlServer">
    <Columns>
      <Column Name="Id" DataType="Int32" Identity="True" PrimaryKey="True" Description="编号" />
      <Column Name="ShopName" DataType="String" Length="200" Description="店铺名称" />
      <Column Name="KId" DataType="Int32" Description="商家分类ID" />
      <Column Name="AId" DataType="Int32" Description="地区ID" />
      <Column Name="Sequence" DataType="Int32" Description="排序" />
      <Column Name="Latitude" DataType="Decimal" Description="纬度" />
      <Column Name="Longitude" DataType="Decimal" Description="经度" />
      <Column Name="Country" DataType="String" Description="国家" />
      <Column Name="Province" DataType="String" Description="省" />
      <Column Name="City" DataType="String" Description="市" />
      <Column Name="District" DataType="String" Description="区" />
      <Column Name="Address" DataType="String" Length="250" Description="详细地址" />
      <Column Name="Postcode" DataType="String" Length="20" Description="邮政编码" />
      <Column Name="IsDel" DataType="Int32" Description="是否删除" />
      <Column Name="IsHide" DataType="Int32" Description="是否隐藏" />
      <Column Name="IsDisabled" DataType="Int32" Description="是否禁用" />
      <Column Name="Content" DataType="String" Length="-1" Description="店铺介绍" />
      <Column Name="Keyword" DataType="String" Length="250" Description="关键字" />
      <Column Name="Description" DataType="String" Length="250" Description="描述" />
      <Column Name="BannerImg" DataType="String" Length="250" Description="banner图片" />
      <Column Name="Balance" DataType="Decimal" Description="余额" />
      <Column Name="IsTop" DataType="Int32" Description="是否置顶" />
      <Column Name="IsVip" DataType="Int32" Description="是否vip" />
      <Column Name="IsRecommend" DataType="Int32" Description="是否推荐" />
      <Column Name="Likes" DataType="Int32" Description="点赞数" />
      <Column Name="AvgScore" DataType="Decimal" Description="平均分数" />
      <Column Name="ServiceScore" DataType="Decimal" Description="服务分数" />
      <Column Name="SpeedScore" DataType="Decimal" Description="速度分数" />
      <Column Name="EnvironmentScore" DataType="Decimal" Description="环境分数" />
      <Column Name="Pic" DataType="String" Length="250" Description="图片" />
      <Column Name="MorePics" DataType="String" Length="-1" Description="店铺所有图片" />
      <Column Name="Email" DataType="String" Length="100" Description="邮箱" />
      <Column Name="Tel" DataType="String" Description="电话" />
      <Column Name="Phone" DataType="String" Description="固定电话" />
      <Column Name="Qq" DataType="String" Length="20" Description="QQ" />
      <Column Name="Skype" DataType="String" Length="100" Description="Skype" />
      <Column Name="HomePage" DataType="String" Length="250" Description="主页" />
      <Column Name="Weixin" DataType="String" Description="微信" />
      <Column Name="IsShip" DataType="Int32" Description="是否配送" />
      <Column Name="OpenTime" DataType="DateTime" Description="开店时间" />
      <Column Name="CloseTime" DataType="DateTime" Description="关店时间" />
      <Column Name="ShippingStartTime" DataType="DateTime" Description="配送开始时间" />
      <Column Name="ShippingEndTime" DataType="DateTime" Description="配送结束时间" />
      <Column Name="AddTime" DataType="DateTime" Description="添加时间" />
      <Column Name="Hits" DataType="Int32" Description="点击量" />
      <Column Name="MyType" DataType="Int32" Description="店铺类型" />
      <Column Name="DefaultFare" DataType="Decimal" Description="默认运费" />
      <Column Name="MaxFreeFare" DataType="Decimal" Description="最大免运费金额" />
    </Columns>
  </Table>
  <Table Name="ShopCategory" Description="商家分类" DbType="SqlServer">
    <Columns>
      <Column Name="Id" DataType="Int32" Identity="True" PrimaryKey="True" Description="编号" />
      <Column Name="KindName" DataType="String" Length="250" Description="栏目名称" />
      <Column Name="SubTitle" DataType="String" Length="250" Description="栏目副标题" />
      <Column Name="KindTitle" DataType="String" Length="250" Description="栏目标题，填写则在浏览器替换此标题" />
      <Column Name="Keyword" DataType="String" Length="250" Description="描述" />
      <Column Name="Description" DataType="String" Length="250" Description="介绍" />
      <Column Name="LinkURL" DataType="String" Length="250" Description="跳转链接" />
      <Column Name="TitleColor" DataType="String" Description="类别名称颜色" />
      <Column Name="TemplateFile" DataType="String" Length="250" Description="模板" />
      <Column Name="DetailTemplateFile" DataType="String" Length="250" Description="详情模板" />
      <Column Name="KindDomain" DataType="String" Length="250" Description="类别域名（保留）" />
      <Column Name="IsList" DataType="Int32" Description="是否为列表页面" />
      <Column Name="PageSize" DataType="Int32" Description="每页显示数量" />
      <Column Name="PId" DataType="Int32" Description="上级ID" />
      <Column Name="Level" DataType="Int32" Description="级别" />
      <Column Name="Location" DataType="String" Length="100" Description="路径" />
      <Column Name="IsHide" DataType="Int32" Description="是否隐藏" />
      <Column Name="IsLock" DataType="Int32" Description="是否锁定，不允许删除" />
      <Column Name="IsDel" DataType="Int32" Description="是否删除,已经删除到回收站" />
      <Column Name="IsComment" DataType="Int32" Description="是否允许评论" />
      <Column Name="IsMember" DataType="Int32" Description="是否会员栏目" />
      <Column Name="IsShowSubDetail" DataType="Int32" Description="是否显示下级栏目内容" />
      <Column Name="CatalogId" DataType="Int32" Description="模型ID" />
      <Column Name="Counts" DataType="Int32" Description="详情数量，缓存" />
      <Column Name="Rank" DataType="Int32" Description="排序" />
      <Column Name="Icon" DataType="String" Length="100" Description="图标" />
      <Column Name="ClassName" DataType="String" Description="样式名称" />
      <Column Name="BannerImg" DataType="String" Length="250" Description="banner图片" />
      <Column Name="KindInfo" DataType="String" Length="-1" Description="栏目详细介绍" />
      <Column Name="Pic" DataType="String" Length="250" Description="图片" />
      <Column Name="AdsId" DataType="Int32" Description="广告ID" />
    </Columns>
  </Table>
  <Table Name="Food" Description="快餐" DbType="SqlServer">
    <Columns>
      <Column Name="Id" DataType="Int32" Identity="True" PrimaryKey="True" Description="编号" />
      <Column Name="KId" DataType="Int32" Description="栏目ID" />
      <Column Name="BId" DataType="Int32" Description="品牌ID" />
      <Column Name="ShopId" DataType="Int32" Description="店铺ID" />
      <Column Name="CId" DataType="Int32" Description="颜色ID" />
      <Column Name="SupportId" DataType="Int32" Description="供货商ID" />
      <Column Name="Title" DataType="String" Master="True" Length="250" Description="标题" />
      <Column Name="ItemNO" DataType="String" Description="编号" />
      <Column Name="SubTitle" DataType="String" Length="250" Description="副标题" />
      <Column Name="Unit" DataType="String" Length="250" Description="商品单位" />
      <Column Name="Spec" DataType="String" Length="250" Description="商品规格尺寸" />
      <Column Name="Color" DataType="String" Length="250" Description="颜色" />
      <Column Name="Weight" DataType="String" Description="重量" />
      <Column Name="Price" DataType="Decimal" Description="价格" />
      <Column Name="MarketPrice" DataType="Decimal" Description="市场价格" />
      <Column Name="SpecialPrice" DataType="Decimal" Description="特价，如有特价，以特价为准" />
      <Column Name="Fare" DataType="Decimal" Description="运费" />
      <Column Name="Discount" DataType="Decimal" Description="折扣" />
      <Column Name="Material" DataType="String" Length="250" Description="材料" />
      <Column Name="Front" DataType="String" Length="250" Description="封面" />
      <Column Name="Credits" DataType="Int32" Description="积分" />
      <Column Name="Stock" DataType="Int32" Description="库存" />
      <Column Name="WarnStock" DataType="Int32" Description="警告库存" />
      <Column Name="IsSubProduct" DataType="Int32" Description="是否为子商品" />
      <Column Name="PPId" DataType="Int32" Description="父商品ID。如果为子商品，则需要填写父商品ID。实现多颜色功能" />
      <Column Name="Content" DataType="String" Length="-1" Description="内容" />
      <Column Name="Parameters" DataType="String" Length="-1" Description="商品参数" />
      <Column Name="Keyword" DataType="String" Length="250" Description="描述" />
      <Column Name="Description" DataType="String" Length="250" Description="介绍" />
      <Column Name="LinkURL" DataType="String" Length="250" Description="跳转链接" />
      <Column Name="TitleColor" DataType="String" Description="类别名称颜色" />
      <Column Name="TemplateFile" DataType="String" Length="250" Description="模板" />
      <Column Name="IsRecommend" DataType="Int32" Description="是否推荐" />
      <Column Name="IsHide" DataType="Int32" Description="是否隐藏" />
      <Column Name="IsLock" DataType="Int32" Description="是否锁定，不允许删除" />
      <Column Name="IsDel" DataType="Int32" Description="是否删除,已经删除到回收站" />
      <Column Name="IsTop" DataType="Int32" Description="是否置顶" />
      <Column Name="IsBest" DataType="Int32" Description="是否精华" />
      <Column Name="IsComment" DataType="Int32" Description="是否允许评论" />
      <Column Name="IsMember" DataType="Int32" Description="是否会员栏目" />
      <Column Name="IsNew" DataType="Int32" Description="是否新品" />
      <Column Name="IsSpecial" DataType="Int32" Description="是否特价" />
      <Column Name="IsPromote" DataType="Int32" Description="是否促销" />
      <Column Name="IsHotSales" DataType="Int32" Description="是否热销" />
      <Column Name="IsBreakup" DataType="Int32" Description="是否缺货" />
      <Column Name="IsShelves" DataType="Int32" Description="是否下架" />
      <Column Name="IsVerify" DataType="Int32" Description="是否审核，1为已经审核前台显示" />
      <Column Name="Hits" DataType="Int32" Description="点击数量" />
      <Column Name="IsGift" DataType="Int32" Description="是否为礼品商品" />
      <Column Name="IsPart" DataType="Int32" Description="是否为配件" />
      <Column Name="Sequence" DataType="Int32" Description="排序" />
      <Column Name="CommentCount" DataType="Int32" Description="评论数量" />
      <Column Name="Icon" DataType="String" Length="100" Description="图标" />
      <Column Name="ClassName" DataType="String" Description="样式名称" />
      <Column Name="BannerImg" DataType="String" Length="250" Description="banner图片" />
      <Column Name="Pic" DataType="String" Length="250" Description="图片" />
      <Column Name="AdsId" DataType="Int32" Description="广告ID" />
      <Column Name="Tags" DataType="String" Length="250" Description="TAG" />
      <Column Name="ItemImg" DataType="String" Length="-1" Description="更多图片" />
      <Column Name="Service" DataType="String" Length="-1" Description="售后服务" />
      <Column Name="AuthorId" DataType="Int32" Description="添加管理员ID" />
      <Column Name="AddTime" DataType="DateTime" Description="添加时间" />
      <Column Name="UpdateTime" DataType="DateTime" Description="时间" />
      <Column Name="Location" DataType="String" Length="100" Description="路径" />
      <Column Name="FilePath" DataType="String" Length="100" Description="存放目录" />
    </Columns>
  </Table>
  <Table Name="HotelRoom" Description="酒店房间" DbType="SqlServer">
    <Columns>
      <Column Name="Id" DataType="Int32" Identity="True" PrimaryKey="True" Description="编号" />
      <Column Name="KId" DataType="Int32" Description="栏目ID" />
      <Column Name="BId" DataType="Int32" Description="品牌ID" />
      <Column Name="ShopId" DataType="Int32" Description="店铺ID" />
      <Column Name="CId" DataType="Int32" Description="颜色ID" />
      <Column Name="SupportId" DataType="Int32" Description="供货商ID" />
      <Column Name="Title" DataType="String" Master="True" Length="250" Description="标题" />
      <Column Name="ItemNO" DataType="String" Description="编号" />
      <Column Name="SubTitle" DataType="String" Length="250" Description="副标题" />
      <Column Name="Unit" DataType="String" Length="250" Description="商品单位" />
      <Column Name="Spec" DataType="String" Length="250" Description="商品规格尺寸" />
      <Column Name="Color" DataType="String" Length="250" Description="颜色" />
      <Column Name="Weight" DataType="String" Description="重量" />
      <Column Name="Price" DataType="Decimal" Description="价格" />
      <Column Name="MarketPrice" DataType="Decimal" Description="市场价格" />
      <Column Name="SpecialPrice" DataType="Decimal" Description="特价，如有特价，以特价为准" />
      <Column Name="Fare" DataType="Decimal" Description="运费" />
      <Column Name="Discount" DataType="Decimal" Description="折扣" />
      <Column Name="Material" DataType="String" Length="250" Description="材料" />
      <Column Name="Front" DataType="String" Length="250" Description="封面" />
      <Column Name="Credits" DataType="Int32" Description="积分" />
      <Column Name="Stock" DataType="Int32" Description="库存" />
      <Column Name="WarnStock" DataType="Int32" Description="警告库存" />
      <Column Name="IsSubProduct" DataType="Int32" Description="是否为子商品" />
      <Column Name="PPId" DataType="Int32" Description="父商品ID。如果为子商品，则需要填写父商品ID。实现多颜色功能" />
      <Column Name="Content" DataType="String" Length="-1" Description="内容" />
      <Column Name="Parameters" DataType="String" Length="-1" Description="商品参数" />
      <Column Name="Keyword" DataType="String" Length="250" Description="描述" />
      <Column Name="Description" DataType="String" Length="250" Description="介绍" />
      <Column Name="LinkURL" DataType="String" Length="250" Description="跳转链接" />
      <Column Name="TitleColor" DataType="String" Description="类别名称颜色" />
      <Column Name="TemplateFile" DataType="String" Length="250" Description="模板" />
      <Column Name="IsRecommend" DataType="Int32" Description="是否推荐" />
      <Column Name="IsHide" DataType="Int32" Description="是否隐藏" />
      <Column Name="IsLock" DataType="Int32" Description="是否锁定，不允许删除" />
      <Column Name="IsDel" DataType="Int32" Description="是否删除,已经删除到回收站" />
      <Column Name="IsTop" DataType="Int32" Description="是否置顶" />
      <Column Name="IsBest" DataType="Int32" Description="是否精华" />
      <Column Name="IsComment" DataType="Int32" Description="是否允许评论" />
      <Column Name="IsMember" DataType="Int32" Description="是否会员栏目" />
      <Column Name="IsNew" DataType="Int32" Description="是否新品" />
      <Column Name="IsSpecial" DataType="Int32" Description="是否特价" />
      <Column Name="IsPromote" DataType="Int32" Description="是否促销" />
      <Column Name="IsHotSales" DataType="Int32" Description="是否热销" />
      <Column Name="IsBreakup" DataType="Int32" Description="是否缺货" />
      <Column Name="IsShelves" DataType="Int32" Description="是否下架" />
      <Column Name="IsVerify" DataType="Int32" Description="是否审核，1为已经审核前台显示" />
      <Column Name="Hits" DataType="Int32" Description="点击数量" />
      <Column Name="IsGift" DataType="Int32" Description="是否为礼品商品" />
      <Column Name="IsPart" DataType="Int32" Description="是否为配件" />
      <Column Name="Sequence" DataType="Int32" Description="排序" />
      <Column Name="CommentCount" DataType="Int32" Description="评论数量" />
      <Column Name="Icon" DataType="String" Length="100" Description="图标" />
      <Column Name="ClassName" DataType="String" Description="样式名称" />
      <Column Name="BannerImg" DataType="String" Length="250" Description="banner图片" />
      <Column Name="Pic" DataType="String" Length="250" Description="图片" />
      <Column Name="AdsId" DataType="Int32" Description="广告ID" />
      <Column Name="Tags" DataType="String" Length="250" Description="TAG" />
      <Column Name="ItemImg" DataType="String" Length="-1" Description="更多图片" />
      <Column Name="Service" DataType="String" Length="-1" Description="售后服务" />
      <Column Name="AuthorId" DataType="Int32" Description="添加管理员ID" />
      <Column Name="AddTime" DataType="DateTime" Description="添加时间" />
      <Column Name="UpdateTime" DataType="DateTime" Description="时间" />
      <Column Name="Location" DataType="String" Length="100" Description="路径" />
      <Column Name="FilePath" DataType="String" Length="100" Description="存放目录" />
      <Column Name="PriceList" DataType="String" Length="-1" Description="日期价格" />
    </Columns>
  </Table>
  <Table Name="WXAppSession" Description="小程序Session" DbType="SqlServer">
    <Columns>
      <Column Name="Id" DataType="Int32" Identity="True" PrimaryKey="True" Description="编号" />
      <Column Name="UId" DataType="Int32" Description="用户ID" />
      <Column Name="Ip" DataType="String" Length="20" Description="登录IP" />
      <Column Name="Key" DataType="String" Description="系统生成Key" />
      <Column Name="SessionKey" DataType="String" Description="微信SessionKey" />
      <Column Name="OpenId" DataType="String" Description="微信小程序OpenId" />
      <Column Name="AddTime" DataType="DateTime" Description="添加时间" />
    </Columns>
  </Table>
  <Table Name="CouponKind" Description="优惠券分类" DbType="SqlServer">
    <Columns>
      <Column Name="Id" DataType="Int32" Identity="True" PrimaryKey="True" Description="编号" />
      <Column Name="IsLimit" DataType="Int32" Description="是否有类别限制，0 无限制；1 是类别限制，2是商品限制" />
      <Column Name="KindName" DataType="String" Length="200" Description="类别名称" />
      <Column Name="CouponType" DataType="Int32" Description="优惠券类型，0 现金用券，1打折券" />
      <Column Name="KIds" DataType="String" Length="-1" Description="类别按逗号分开" />
      <Column Name="PIds" DataType="String" Length="-1" Description="商品ID，按逗号分开" />
      <Column Name="KindNote" DataType="String" Length="250" Description="类别说明" />
      <Column Name="AddTime" DataType="DateTime" Description="添加时间" />
      <Column Name="MyType" DataType="Int32" Description="可使用类型" />
    </Columns>
  </Table>
  <Table Name="Coupon" Description="优惠券" DbType="SqlServer">
    <Columns>
      <Column Name="Id" DataType="Int32" Identity="True" PrimaryKey="True" Description="编号" />
      <Column Name="ItemNO" DataType="String" Length="20" Description="券号" />
      <Column Name="KId" DataType="Int32" Description="类别，0默认没限制" />
      <Column Name="CouponType" DataType="Int32" Description="优惠券类型，0 现金用券，1打折券" />
      <Column Name="DiscuountRates" DataType="Decimal" Description="打折率，只有是打折券才有用" />
      <Column Name="IsLimit" DataType="Int32" Description="是否有类别限制，0 无限制；1 是类别限制，2是商品限制" />
      <Column Name="Price" DataType="Decimal" Description="面额" />
      <Column Name="NeedPrice" DataType="Decimal" Description="需要消费面额" />
      <Column Name="AddTime" DataType="DateTime" Description="添加时间" />
      <Column Name="StartTime" DataType="DateTime" Description="添加时间" />
      <Column Name="EndTime" DataType="DateTime" Description="添加时间" />
      <Column Name="TotalCount" DataType="Int32" Description="最大领取数量" />
      <Column Name="TotalUseCount" DataType="Int32" Description="已使用次数" />
      <Column Name="SpreadUId" DataType="Int32" Description="推广员ID，可选" />
      <Column Name="UId" DataType="Int32" Description="用户Id" />
      <Column Name="MyType" DataType="Int32" Description="可使用类型" />
    </Columns>
  </Table>
  <Table Name="CouponUseLog" Description="优惠券使用记录" DbType="SqlServer">
    <Columns>
      <Column Name="Id" DataType="Int32" Identity="True" PrimaryKey="True" Description="编号" />
      <Column Name="UId" DataType="Int32" Master="True" Description="用户ID" />
      <Column Name="CouponId" DataType="Int32" Description="优惠券ID" />
      <Column Name="ItemNO" DataType="String" Length="20" Description="优惠券编号" />
      <Column Name="OrderNum" DataType="String" Description="订单号" />
      <Column Name="OrderId" DataType="Int32" Description="订单编号" />
      <Column Name="UserName" DataType="String" Length="200" Description="用户名" />
      <Column Name="Title" DataType="String" Length="200" Description="订单名称" />
      <Column Name="AddTime" DataType="DateTime" Description="时间" />
      <Column Name="Ip" DataType="String" Length="20" Description="登录IP" />
      <Column Name="Actions" DataType="String" Length="250" Description="记录详情" />
    </Columns>
  </Table>
  <Table Name="MemberCoupon" Description="用户优惠券" DbType="SqlServer">
    <Columns>
      <Column Name="Id" DataType="Int32" Identity="True" PrimaryKey="True" Description="编号" />
      <Column Name="UId" DataType="Int32" Master="True" Description="用户ID" />
      <Column Name="ItemNO" DataType="String" Length="20" Description="券号" />
      <Column Name="CouponId" DataType="Int32" Description="优惠券ID" />
      <Column Name="CouponType" DataType="Int32" Description="优惠券类型，0 现金用券，1打折券" />
      <Column Name="DiscuountRates" DataType="Decimal" Description="打折率，只有是打折券才有用" />
      <Column Name="IsLimit" DataType="Int32" Description="是否有类别限制，0 无限制；1 是类别限制，2是商品限制" />
      <Column Name="Price" DataType="Decimal" Description="面额" />
      <Column Name="NeedPrice" DataType="Decimal" Description="需要消费面额" />
      <Column Name="AddTime" DataType="DateTime" Description="添加时间" />
      <Column Name="StartTime" DataType="DateTime" Description="添加时间" />
      <Column Name="EndTime" DataType="DateTime" Description="添加时间" />
      <Column Name="IsUse" DataType="Int32" Description="是否使用" />
      <Column Name="UseTime" DataType="DateTime" Description="使用时间" />
      <Column Name="OrderNum" DataType="String" Description="订单号（使用后）" />
      <Column Name="OrderId" DataType="Int32" Description="订单编号（使用后）" />
    </Columns>
  </Table>
  <Table Name="WithdrawOrder" Description="用户提现订单" DbType="SqlServer">
    <Columns>
      <Column Name="Id" DataType="Int32" Identity="True" PrimaryKey="True" Description="编号" />
      <Column Name="UId" DataType="Int32" Master="True" Description="用户ID" />
      <Column Name="OrderNum" DataType="String" Description="订单号" />
      <Column Name="UserName" DataType="String" Length="200" Description="用户名" />
      <Column Name="Title" DataType="String" Master="True" Length="100" Description="订单名称" />
      <Column Name="AddTime" DataType="DateTime" Description="时间" />
      <Column Name="Ip" DataType="String" Length="20" Description="登录IP" />
      <Column Name="Actions" DataType="String" Master="True" Length="250" Description="记录详情" />
      <Column Name="Price" DataType="Decimal" Description="提现金额" />
      <Column Name="VerifyAdminId" DataType="Int32" Description="审核管理员ID" />
      <Column Name="IsVerify" DataType="Int32" Description="是否通过审核" />
      <Column Name="VerifyTime" DataType="DateTime" Description="审核时间" />
      <Column Name="FormId" DataType="String" Description="小程序FormId" />
    </Columns>
  </Table>
  <Table Name="WeixinRequestRule" Description="微信公众号回复规则" DbType="SqlServer">
    <Columns>
      <Column Name="Id" DataType="Int32" Identity="True" PrimaryKey="True" Description="编号" />
      <Column Name="RuleName" DataType="String" Description="规则名称" />
      <Column Name="Keywords" DataType="String" Length="200" Description="请求关键词,逗号分隔" />
      <Column Name="RequestType" DataType="Int32" Description="请求类型(0默认回复1文字2图片3语音4链接5地理位置6关注7取消关注8扫描带参数二维码事件9上报地理位置事件10自定义菜单事件）" />
      <Column Name="ResponseType" DataType="Int32" Description="回复类型(1文本2图文3语音4视频5第三方接口)" />
      <Column Name="IsLikeQuery" DataType="Int32" Description="是否模糊查询 0 是完全匹配；1是模糊匹配" />
      <Column Name="IsDefault" DataType="Int32" Description="是否是默认回复" />
      <Column Name="Rank" DataType="Int32" Description="排序" />
      <Column Name="AddTime" DataType="DateTime" Description="添加时间" />
      <Column Name="UpdateTime" DataType="DateTime" Description="修改时间" />
    </Columns>
  </Table>
  <Table Name="WeixinRequestContent" Description="请求回复的内容" DbType="SqlServer">
    <Columns>
      <Column Name="Id" DataType="Int32" Identity="True" PrimaryKey="True" Description="编号" />
      <Column Name="RuleId" DataType="Int32" Description="规则名称" />
      <Column Name="Title" DataType="String" Master="True" Length="250" Description="回复标题" />
      <Column Name="Content" DataType="String" Length="-1" Description="回复内容" />
      <Column Name="LinkUrl" DataType="String" Length="250" Description="详情链接地址" />
      <Column Name="ImgURL" DataType="String" Length="250" Description="图片地址" />
      <Column Name="MediaURL" DataType="String" Length="250" Description="语音或视频地址" />
      <Column Name="MeidaHdURL" DataType="String" Length="250" Description="高清语音或者视频地址" />
      <Column Name="MediaID" DataType="String" Length="100" Description="返回的素材ID" />
      <Column Name="WXAppAppId" DataType="String" Length="100" Description="小程序APPId" />
      <Column Name="WXAppPage" DataType="String" Length="100" Description="小程序页面" />
      <Column Name="Rank" DataType="Int32" Description="排序" />
      <Column Name="AddTime" DataType="DateTime" Description="添加时间" />
      <Column Name="UpdateTime" DataType="DateTime" Description="修改时间" />
    </Columns>
  </Table>
  <Table Name="WeixinResponseContent" Description="公众平台回复信息" DbType="SqlServer">
    <Columns>
      <Column Name="Id" DataType="Int32" Identity="True" PrimaryKey="True" Description="编号" />
      <Column Name="OpenId" DataType="String" Description="用户OpenId" />
      <Column Name="RequestType" DataType="String" Description="请求类型" />
      <Column Name="RequestContent" DataType="String" Length="-1" Description="内容" />
      <Column Name="ResponseType" DataType="String" Description="回复的类型 文本消息：text 图片消息:image 地理位置消息:location 链接消息:link" />
      <Column Name="ReponseContent" DataType="String" Length="-1" Description="系统回复的内容" />
      <Column Name="XmlContent" DataType="String" Length="-1" Description="xml原始内容" />
      <Column Name="UpdateTime" DataType="DateTime" Description="修改时间" />
    </Columns>
  </Table>
  <Table Name="Department" Description="部门" DbType="SqlServer">
    <Columns>
      <Column Name="Id" DataType="Int32" Identity="True" PrimaryKey="True" Description="编号" />
      <Column Name="DepartmentName" DataType="String" Description="部门名称" />
      <Column Name="PId" DataType="Int32" Description="上级部门ID" />
      <Column Name="Level" DataType="Int32" Description="级别" />
      <Column Name="Location" DataType="String" Length="100" Description="路径" />
      <Column Name="DepartmentDescription" DataType="String" Length="250" Description="部门说明" />
      <Column Name="Pic" DataType="String" Length="250" Description="部门图片" />
      <Column Name="Rank" DataType="Int32" Description="排序" />
      <Column Name="IsNotAllowDel" DataType="Int32" Description="是否不允许删除" />
      <Column Name="Powers" DataType="String" Master="True" Length="-1" Description="部门权限" />
      <Column Name="IsDel" DataType="Int32" Description="是否删除" />
      <Column Name="Tel" DataType="String" Length="30" Description="联系电话" />
      <Column Name="Fax" DataType="String" Length="30" Description="传真" />
      <Column Name="Email" DataType="String" Length="100" Description="邮件" />
    </Columns>
  </Table>
  <Table Name="DataDictionary" Description="数据字典" DbType="SqlServer">
    <Columns>
      <Column Name="Id" DataType="Int32" Identity="True" PrimaryKey="True" Description="编号" />
      <Column Name="Key" DataType="String" Description="字典key" />
      <Column Name="Description" DataType="String" Description="字典介绍" />
      <Column Name="Rank" DataType="Int32" Description="排序" />
      <Column Name="AddTime" DataType="DateTime" Description="添加时间" />
    </Columns>
  </Table>
  <Table Name="DataDictionaryDetail" Description="数据字典详情" DbType="SqlServer">
    <Columns>
      <Column Name="Id" DataType="Int32" Identity="True" PrimaryKey="True" Description="编号" />
      <Column Name="DataDictionaryId" DataType="Int32" Description="字典ID" />
      <Column Name="Val" DataType="String" Description="字典值" />
      <Column Name="Title" DataType="String" Master="True" Description="字典标签" />
      <Column Name="Description" DataType="String" Description="字典介绍" />
      <Column Name="Rank" DataType="Int32" Description="排序" />
      <Column Name="IsDefault" DataType="Int32" Description="是否默认值" />
      <Column Name="AddTime" DataType="DateTime" Description="添加时间" />
    </Columns>
  </Table>
</Tables>